MANIFEST.in
README.rst
setup.cfg
setup.py
appdo/__init__.py
appdo/appdo.py
appdo.egg-info/PKG-INFO
appdo.egg-info/SOURCES.txt
appdo.egg-info/dependency_links.txt
appdo.egg-info/requires.txt
appdo.egg-info/top_level.txt
appdo/tests/__init__.py
docs/Makefile
docs/source/CHANGELOG.rst
docs/source/README.rst
docs/source/conf.py
docs/source/index.rst
docs/source/modules/index.rst
scripts/appdo